{
  "wallet_address": "0xcaFB99c260635184a6336E4B48982976cdFB960E",
  "issued_at_utc": "2026-05-31T09:39:55.765805+00:00",
  "receipt_id": "29901e9882bb1af7c963f56dedb8c95bf54587bfaeb3ea8eeab89994c8bc0399",
  "status": "READY_FOR_MINT",
  "co2_nanograms": 2500000000,
  "joules_millijoules": 8815243104220,
  "arctic_nanomm2": 2026218296200,
  "lovelock_basis_points": 6600,
  "proof_fingerprint": "39ebbbb99323ff1f66f309720c739e80b8a4f571a5e229d18cfdc27342a71872",
  "co2_tonnes_display": 0.0025,
  "arctic_mm2_display": 2026218.2962,
  "ipcc_co2_score": 0.4647,
  "ipcc_temp_score": 0.812,
  "ipcc_humidity_score": 0.8022,
  "ipcc_lat_factor": 0.85,
  "ipcc_methodology": "IPCC_AR6_WGI_Table5.1",
  "env_temperature_c": 30.14,
  "env_humidity_pct": 80.22,
  "env_data_source": "NASA-POWER-API-v2.9",
  "env_verified": true,
  "env_layer_used": 1,
  "off_chain_proof_id": "0x71f6a080d73258c33ada5c81856caf567eddd19fdef1fdda0552d4a1d1c8063f",
  "on_chain_tx": null,
  "blockchain_provider": "Amoy-Public",
  "mint_latency_ms": 289.56,
  "block_number": 39326516,
  "human_message": "Your action just cooled a 2026218.2962 mm\u00b2 patch of the Arctic. This contributes 0.0000000000% toward the 2050 preservation goal. Verified on-chain: 0x71f6a080d73258...",
  "receipt_hash": "06bb97fc698d9190e1b13798e59a74c6b70fec091f9f0b5950c83ea8121161fa",
  "oracle_signature": "0x5edc397145e70341db2b3ef00976fc164b0f4e38dcdb4f9fac3f90e60f007b1d37fe7f48cb664b657336f692cb43b1d7aa6bc717d4200a882a98311ebc24270f1b"
}